lark_sentry/__init__.py
lark_sentry/plugin.py
lark_sentry-2.2.1.dist-info/METADATA
lark_sentry-2.2.1.dist-info/WHEEL
lark_sentry-2.2.1.dist-info/entry_points.txt
lark_sentry-2.2.1.dist-info/top_level.txt
lark_sentry-2.2.1.dist-info/RECORD
