Metadata-Version: 2.1
Name: lark-sentry
Version: 2.2.1
Summary: Plugin for Sentry which allows sending notification via Lark messenger.
Home-page: https://github.com/x0216u/lark_sentry
Author: x0216u
Author-email: x0216u@gmail.com
License: MIT
Platform: UNKNOWN
Classifier: Development Status :: 5 - Production/Stable
Classifier: Environment :: Console
Classifier: Intended Audience :: Developers
Classifier: Intended Audience :: System Administrators
Classifier: License :: OSI Approved :: MIT License
Classifier: Operating System :: OS Independent
Classifier: Programming Language :: Python
Classifier: Programming Language :: Python :: 2.7
Classifier: Programming Language :: Python :: Implementation :: CPython
Classifier: Topic :: Software Development :: Bug Tracking
Classifier: Topic :: Software Development :: Quality Assurance
Classifier: Topic :: System :: Monitoring
Requires-Dist: sentry (>=9.1.2)
